django_meta_og/__init__.py
django_meta_og/admin.py
django_meta_og/apps.py
django_meta_og/context_processors.py
django_meta_og/dynamic_content.py
django_meta_og/utils.py
django_meta_og/locale/cs/LC_MESSAGES/django.po
django_meta_og/migrations/0001_initial.py
django_meta_og/migrations/0002_default_properties.py
django_meta_og/migrations/__init__.py
django_meta_og/models/__init__.py
django_meta_og/models/content.py
django_meta_og/models/namespace.py
django_meta_og/models/property.py
django_meta_og/templates/admin/django_meta_og/content/change_form.html
django_meta_og/templates/django_meta_og/header_meta.html
django_meta_og/templatetags/__init__.py
django_meta_og/templatetags/django_meta_og.py
django_meta_og/tests/__init__.py
django_meta_og/tests/settings.py
django_meta_og/tests/test_admin.py
django_meta_og/tests/test_context_processors.py
django_meta_og/tests/test_models.py
django_meta_og/tests/test_templates.py
django_meta_og/tests/test_templatetags.py
django_meta_og/tests/test_utils.py
django_meta_og/tests/urls.py
django_meta_og-2.0.0.dist-info/METADATA
django_meta_og-2.0.0.dist-info/WHEEL
django_meta_og-2.0.0.dist-info/top_level.txt
django_meta_og-2.0.0.dist-info/RECORD
