Metadata-Version: 2.2
Name: django-meta-og
Version: 2.0.0
Summary: Django HTML Meta tags for OpenGraph.
Author-email: Zdeněk Böhm <zdenek.bohm@nic.cz>
License: BSD License
Project-URL: Homepage, https://gitlab.nic.cz/django-apps/django-meta-og
Project-URL: Repository, https://gitlab.nic.cz/django-apps/django-meta-og.git
Classifier: Development Status :: 5 - Production/Stable
Classifier: Environment :: Web Environment
Classifier: Intended Audience :: Developers
Classifier: License :: OSI Approved :: BSD License
Classifier: Operating System :: OS Independent
Classifier: Programming Language :: Python :: 3
Classifier: Programming Language :: Python :: 3.9
Classifier: Programming Language :: Python :: 3.10
Classifier: Programming Language :: Python :: 3.11
Classifier: Programming Language :: Python :: 3.12
Classifier: Framework :: Django
Classifier: Framework :: Django :: 4.2
Classifier: Framework :: Django :: 5.0
Classifier: Topic :: Internet :: WWW/HTTP
Classifier: Topic :: Internet :: WWW/HTTP :: Dynamic Content
Classifier: Topic :: Software Development
Classifier: Topic :: Software Development :: Libraries
Classifier: Topic :: Software Development :: Libraries :: Application Frameworks
Requires-Python: >=3.9
Requires-Dist: django>=4.2
